LICENSE
LICENSE.txt
MANIFEST.in
README.md
setup.cfg
setup.py
pycustomcalcmine/__init__.py
pycustomcalcmine/app.py
pycustomcalcmine/mycalculator.py
pycustomcalcmine.egg-info/PKG-INFO
pycustomcalcmine.egg-info/SOURCES.txt
pycustomcalcmine.egg-info/dependency_links.txt
pycustomcalcmine.egg-info/entry_points.txt
pycustomcalcmine.egg-info/requires.txt
pycustomcalcmine.egg-info/top_level.txt
pycustomcalcmine/static/index.html
pycustomcalcmine/static/css/main.css
pycustomcalcmine/static/css/style.css
pycustomcalcmine/templates/index.html
pycustomcalcmine/templates/results.html